{
  "Response": {
    "Data": [
      {
        "TypeKey": "1312305222",
        "TypeValue": [
          {
            "Avg": 23934972,
            "Detail": [
              {
                "Timestamp": 1766024400,
                "Value": 25489666
              },
              {
                "Timestamp": 1766024700,
                "Value": 20491376
              },
              {
                "Timestamp": 1766025000,
                "Value": 22409355
              },
              {
                "Timestamp": 1766025300,
                "Value": 21048426
              },
              {
                "Timestamp": 1766025600,
                "Value": 22976599
              },
              {
                "Timestamp": 1766025900,
                "Value": 20359371
              },
              {
                "Timestamp": 1766026200,
                "Value": 24198836
              },
              {
                "Timestamp": 1766026500,
                "Value": 26291981
              },
              {
                "Timestamp": 1766026800,
                "Value": 23408550
              },
              {
                "Timestamp": 1766027100,
                "Value": 24027564
              },
              {
                "Timestamp": 1766027400,
                "Value": 24235968
              },
              {
                "Timestamp": 1766027700,
                "Value": 26527870
              },
              {
                "Timestamp": 1766028000,
                "Value": 23972200
              },
              {
                "Timestamp": 1766028300,
                "Value": 24472640
              },
              {
                "Timestamp": 1766028600,
                "Value": 27959379
              },
              {
                "Timestamp": 1766028900,
                "Value": 27470591
              },
              {
                "Timestamp": 1766029200,
                "Value": 25418123
              },
              {
                "Timestamp": 1766029500,
                "Value": 25841024
              },
              {
                "Timestamp": 1766029800,
                "Value": 23645008
              },
              {
                "Timestamp": 1766030100,
                "Value": 20828663
              },
              {
                "Timestamp": 1766030400,
                "Value": 19127022
              },
              {
                "Timestamp": 1766030700,
                "Value": 18500716
              },
              {
                "Timestamp": 1766031000,
                "Value": 19451432
              },
              {
                "Timestamp": 1766031300,
                "Value": 22321000
              },
              {
                "Timestamp": 1766031600,
                "Value": 22634345
              },
              {
                "Timestamp": 1766031900,
                "Value": 26732878
              },
              {
                "Timestamp": 1766032200,
                "Value": 29172055
              },
              {
                "Timestamp": 1766032500,
                "Value": 28499576
              },
              {
                "Timestamp": 1766032800,
                "Value": 26895454
              },
              {
                "Timestamp": 1766033100,
                "Value": 24083933
              },
              {
                "Timestamp": 1766033400,
                "Value": 24144644
              },
              {
                "Timestamp": 1766033700,
                "Value": 22524484
              },
              {
                "Timestamp": 1766034000,
                "Value": 21065338
              },
              {
                "Timestamp": 1766034300,
                "Value": 22560331
              },
              {
                "Timestamp": 1766034600,
                "Value": 20003133
              },
              {
                "Timestamp": 1766034900,
                "Value": 22237542
              },
              {
                "Timestamp": 1766035200,
                "Value": 21185751
              },
              {
                "Timestamp": 1766035500,
                "Value": 20438275
              },
              {
                "Timestamp": 1766035800,
                "Value": 17956194
              },
              {
                "Timestamp": 1766036100,
                "Value": 20710868
              },
              {
                "Timestamp": 1766036400,
                "Value": 21812936
              },
              {
                "Timestamp": 1766036700,
                "Value": 25914493
              },
              {
                "Timestamp": 1766037000,
                "Value": 22821059
              },
              {
                "Timestamp": 1766037300,
                "Value": 22426762
              },
              {
                "Timestamp": 1766037600,
                "Value": 25531730
              },
              {
                "Timestamp": 1766037900,
                "Value": 24015285
              },
              {
                "Timestamp": 1766038200,
                "Value": 24884013
              },
              {
                "Timestamp": 1766038500,
                "Value": 26185898
              },
              {
                "Timestamp": 1766038800,
                "Value": 21999557
              },
              {
                "Timestamp": 1766039100,
                "Value": 23414905
              },
              {
                "Timestamp": 1766039400,
                "Value": 21935702
              },
              {
                "Timestamp": 1766039700,
                "Value": 23411412
              },
              {
                "Timestamp": 1766040000,
                "Value": 21094937
              },
              {
                "Timestamp": 1766040300,
                "Value": 23086199
              },
              {
                "Timestamp": 1766040600,
                "Value": 24908331
              },
              {
                "Timestamp": 1766040900,
                "Value": 27822591
              },
              {
                "Timestamp": 1766041200,
                "Value": 26318059
              },
              {
                "Timestamp": 1766041500,
                "Value": 21248821
              },
              {
                "Timestamp": 1766041800,
                "Value": 22511287
              },
              {
                "Timestamp": 1766042100,
                "Value": 22585621
              },
              {
                "Timestamp": 1766042400,
                "Value": 25653508
              },
              {
                "Timestamp": 1766042700,
                "Value": 24475133
              },
              {
                "Timestamp": 1766043000,
                "Value": 24813892
              },
              {
                "Timestamp": 1766043300,
                "Value": 26060106
              },
              {
                "Timestamp": 1766043600,
                "Value": 24178642
              },
              {
                "Timestamp": 1766043900,
                "Value": 24622090
              },
              {
                "Timestamp": 1766044200,
                "Value": 20856966
              },
              {
                "Timestamp": 1766044500,
                "Value": 19431086
              },
              {
                "Timestamp": 1766044800,
                "Value": 16834192
              },
              {
                "Timestamp": 1766045100,
                "Value": 16110005
              },
              {
                "Timestamp": 1766045400,
                "Value": 20953491
              },
              {
                "Timestamp": 1766045700,
                "Value": 23139768
              },
              {
                "Timestamp": 1766046000,
                "Value": 20089319
              },
              {
                "Timestamp": 1766046300,
                "Value": 24261639
              },
              {
                "Timestamp": 1766046600,
                "Value": 23907293
              },
              {
                "Timestamp": 1766046900,
                "Value": 23881521
              },
              {
                "Timestamp": 1766047200,
                "Value": 24773936
              },
              {
                "Timestamp": 1766047500,
                "Value": 21860602
              },
              {
                "Timestamp": 1766047800,
                "Value": 23229262
              },
              {
                "Timestamp": 1766048100,
                "Value": 19524656
              },
              {
                "Timestamp": 1766048400,
                "Value": 19050948
              },
              {
                "Timestamp": 1766048700,
                "Value": 21355020
              },
              {
                "Timestamp": 1766049000,
                "Value": 18637633
              },
              {
                "Timestamp": 1766049300,
                "Value": 21520542
              },
              {
                "Timestamp": 1766049600,
                "Value": 21095992
              },
              {
                "Timestamp": 1766049900,
                "Value": 20906153
              },
              {
                "Timestamp": 1766050200,
                "Value": 22180918
              },
              {
                "Timestamp": 1766050500,
                "Value": 26079270
              },
              {
                "Timestamp": 1766050800,
                "Value": 26244545
              },
              {
                "Timestamp": 1766051100,
                "Value": 28713462
              },
              {
                "Timestamp": 1766051400,
                "Value": 25498413
              },
              {
                "Timestamp": 1766051700,
                "Value": 23200357
              },
              {
                "Timestamp": 1766052000,
                "Value": 24093729
              },
              {
                "Timestamp": 1766052300,
                "Value": 24795943
              },
              {
                "Timestamp": 1766052600,
                "Value": 29425560
              },
              {
                "Timestamp": 1766052900,
                "Value": 27765327
              },
              {
                "Timestamp": 1766053200,
                "Value": 25485157
              },
              {
                "Timestamp": 1766053500,
                "Value": 27900732
              },
              {
                "Timestamp": 1766053800,
                "Value": 28200273
              },
              {
                "Timestamp": 1766054100,
                "Value": 23451383
              },
              {
                "Timestamp": 1766054400,
                "Value": 26093719
              },
              {
                "Timestamp": 1766054700,
                "Value": 26036235
              },
              {
                "Timestamp": 1766055000,
                "Value": 27772898
              },
              {
                "Timestamp": 1766055300,
                "Value": 29071893
              },
              {
                "Timestamp": 1766055600,
                "Value": 27076600
              },
              {
                "Timestamp": 1766055900,
                "Value": 25117586
              },
              {
                "Timestamp": 1766056200,
                "Value": 28920004
              },
              {
                "Timestamp": 1766056500,
                "Value": 27937353
              },
              {
                "Timestamp": 1766056800,
                "Value": 27705024
              },
              {
                "Timestamp": 1766057100,
                "Value": 24802526
              },
              {
                "Timestamp": 1766057400,
                "Value": 25141201
              },
              {
                "Timestamp": 1766057700,
                "Value": 22933810
              },
              {
                "Timestamp": 1766058000,
                "Value": 24797639
              },
              {
                "Timestamp": 1766058300,
                "Value": 24958113
              },
              {
                "Timestamp": 1766058600,
                "Value": 23028480
              },
              {
                "Timestamp": 1766058900,
                "Value": 19894093
              },
              {
                "Timestamp": 1766059200,
                "Value": 19321875
              },
              {
                "Timestamp": 1766059500,
                "Value": 20318297
              },
              {
                "Timestamp": 1766059800,
                "Value": 22886670
              },
              {
                "Timestamp": 1766060100,
                "Value": 21304735
              },
              {
                "Timestamp": 1766060400,
                "Value": 21998297
              },
              {
                "Timestamp": 1766060700,
                "Value": 24749812
              },
              {
                "Timestamp": 1766061000,
                "Value": 25897619
              },
              {
                "Timestamp": 1766061300,
                "Value": 24133605
              },
              {
                "Timestamp": 1766061600,
                "Value": 25221484
              },
              {
                "Timestamp": 1766061900,
                "Value": 21562505
              },
              {
                "Timestamp": 1766062200,
                "Value": 19515081
              },
              {
                "Timestamp": 1766062500,
                "Value": 21704854
              },
              {
                "Timestamp": 1766062800,
                "Value": 19613165
              },
              {
                "Timestamp": 1766063100,
                "Value": 18827538
              },
              {
                "Timestamp": 1766063400,
                "Value": 17482539
              },
              {
                "Timestamp": 1766063700,
                "Value": 20533942
              },
              {
                "Timestamp": 1766064000,
                "Value": 22160541
              },
              {
                "Timestamp": 1766064300,
                "Value": 20268671
              },
              {
                "Timestamp": 1766064600,
                "Value": 19070644
              },
              {
                "Timestamp": 1766064900,
                "Value": 21994790
              },
              {
                "Timestamp": 1766065200,
                "Value": 25347586
              },
              {
                "Timestamp": 1766065500,
                "Value": 28127085
              },
              {
                "Timestamp": 1766065800,
                "Value": 22750852
              },
              {
                "Timestamp": 1766066100,
                "Value": 21270375
              },
              {
                "Timestamp": 1766066400,
                "Value": 22791304
              },
              {
                "Timestamp": 1766066700,
                "Value": 27700649
              },
              {
                "Timestamp": 1766067000,
                "Value": 27002157
              },
              {
                "Timestamp": 1766067300,
                "Value": 28283372
              },
              {
                "Timestamp": 1766067600,
                "Value": 25118837
              },
              {
                "Timestamp": 1766067900,
                "Value": 22201734
              },
              {
                "Timestamp": 1766068200,
                "Value": 22107290
              },
              {
                "Timestamp": 1766068500,
                "Value": 21507692
              },
              {
                "Timestamp": 1766068800,
                "Value": 26418402
              },
              {
                "Timestamp": 1766069100,
                "Value": 25470386
              },
              {
                "Timestamp": 1766069400,
                "Value": 26927666
              },
              {
                "Timestamp": 1766069700,
                "Value": 27492043
              },
              {
                "Timestamp": 1766070000,
                "Value": 23666669
              },
              {
                "Timestamp": 1766070300,
                "Value": 21548700
              },
              {
                "Timestamp": 1766070600,
                "Value": 24722158
              },
              {
                "Timestamp": 1766070900,
                "Value": 27153917
              },
              {
                "Timestamp": 1766071200,
                "Value": 26574545
              },
              {
                "Timestamp": 1766071500,
                "Value": 26676591
              },
              {
                "Timestamp": 1766071800,
                "Value": 26320999
              },
              {
                "Timestamp": 1766072100,
                "Value": 25606773
              },
              {
                "Timestamp": 1766072400,
                "Value": 25828579
              },
              {
                "Timestamp": 1766072700,
                "Value": 24292254
              },
              {
                "Timestamp": 1766073000,
                "Value": 25618788
              },
              {
                "Timestamp": 1766073300,
                "Value": 18053617
              },
              {
                "Timestamp": 1766073600,
                "Value": 16820176
              },
              {
                "Timestamp": 1766073900,
                "Value": 16940331
              },
              {
                "Timestamp": 1766074200,
                "Value": 21299514
              },
              {
                "Timestamp": 1766074500,
                "Value": 20460541
              },
              {
                "Timestamp": 1766074800,
                "Value": 21638162
              },
              {
                "Timestamp": 1766075100,
                "Value": 29537052
              },
              {
                "Timestamp": 1766075400,
                "Value": 27699592
              },
              {
                "Timestamp": 1766075700,
                "Value": 28124335
              },
              {
                "Timestamp": 1766076000,
                "Value": 27119656
              },
              {
                "Timestamp": 1766076300,
                "Value": 24712301
              },
              {
                "Timestamp": 1766076600,
                "Value": 25151946
              },
              {
                "Timestamp": 1766076900,
                "Value": 22341051
              },
              {
                "Timestamp": 1766077200,
                "Value": 21790671
              },
              {
                "Timestamp": 1766077500,
                "Value": 20778373
              },
              {
                "Timestamp": 1766077800,
                "Value": 21329568
              },
              {
                "Timestamp": 1766078100,
                "Value": 20838200
              },
              {
                "Timestamp": 1766078400,
                "Value": 18825701
              },
              {
                "Timestamp": 1766078700,
                "Value": 18550591
              },
              {
                "Timestamp": 1766079000,
                "Value": 16187716
              },
              {
                "Timestamp": 1766079300,
                "Value": 16690315
              },
              {
                "Timestamp": 1766079600,
                "Value": 20129712
              },
              {
                "Timestamp": 1766079900,
                "Value": 24333094
              },
              {
                "Timestamp": 1766080200,
                "Value": 24833382
              },
              {
                "Timestamp": 1766080500,
                "Value": 21915169
              },
              {
                "Timestamp": 1766080800,
                "Value": 22262100
              },
              {
                "Timestamp": 1766081100,
                "Value": 24614673
              },
              {
                "Timestamp": 1766081400,
                "Value": 26147409
              },
              {
                "Timestamp": 1766081700,
                "Value": 24213930
              },
              {
                "Timestamp": 1766082000,
                "Value": 23929304
              },
              {
                "Timestamp": 1766082300,
                "Value": 20629121
              },
              {
                "Timestamp": 1766082600,
                "Value": 20420788
              },
              {
                "Timestamp": 1766082900,
                "Value": 20982392
              },
              {
                "Timestamp": 1766083200,
                "Value": 20201829
              },
              {
                "Timestamp": 1766083500,
                "Value": 24095601
              },
              {
                "Timestamp": 1766083800,
                "Value": 24705893
              },
              {
                "Timestamp": 1766084100,
                "Value": 25942248
              },
              {
                "Timestamp": 1766084400,
                "Value": 23210702
              },
              {
                "Timestamp": 1766084700,
                "Value": 22885447
              },
              {
                "Timestamp": 1766085000,
                "Value": 21763947
              },
              {
                "Timestamp": 1766085300,
                "Value": 24988046
              },
              {
                "Timestamp": 1766085600,
                "Value": 298793166
              },
              {
                "Timestamp": 1766085900,
                "Value": 23627754
              },
              {
                "Timestamp": 1766086200,
                "Value": 21151615
              },
              {
                "Timestamp": 1766086500,
                "Value": 21124225
              },
              {
                "Timestamp": 1766086800,
                "Value": 20644756
              },
              {
                "Timestamp": 1766087100,
                "Value": 23480719
              },
              {
                "Timestamp": 1766087400,
                "Value": 20818360
              },
              {
                "Timestamp": 1766087700,
                "Value": 16616538
              },
              {
                "Timestamp": 1766088000,
                "Value": 14602350
              },
              {
                "Timestamp": 1766088300,
                "Value": 17653255
              },
              {
                "Timestamp": 1766088600,
                "Value": 18328133
              },
              {
                "Timestamp": 1766088900,
                "Value": 19886446
              },
              {
                "Timestamp": 1766089200,
                "Value": 21389540
              },
              {
                "Timestamp": 1766089500,
                "Value": 21397637
              },
              {
                "Timestamp": 1766089800,
                "Value": 22311403
              },
              {
                "Timestamp": 1766090100,
                "Value": 24706445
              },
              {
                "Timestamp": 1766090400,
                "Value": 21849439
              },
              {
                "Timestamp": 1766090700,
                "Value": 23475284
              },
              {
                "Timestamp": 1766091000,
                "Value": 19304868
              },
              {
                "Timestamp": 1766091300,
                "Value": 19916196
              },
              {
                "Timestamp": 1766091600,
                "Value": 18290244
              },
              {
                "Timestamp": 1766091900,
                "Value": 15462013
              },
              {
                "Timestamp": 1766092200,
                "Value": 19119847
              },
              {
                "Timestamp": 1766092500,
                "Value": 20829736
              },
              {
                "Timestamp": 1766092800,
                "Value": 23660245
              },
              {
                "Timestamp": 1766093100,
                "Value": 19156800
              },
              {
                "Timestamp": 1766093400,
                "Value": 21796926
              },
              {
                "Timestamp": 1766093700,
                "Value": 24165942
              },
              {
                "Timestamp": 1766094000,
                "Value": 27562431
              },
              {
                "Timestamp": 1766094300,
                "Value": 27642357
              },
              {
                "Timestamp": 1766094600,
                "Value": 25220345
              },
              {
                "Timestamp": 1766094900,
                "Value": 22441130
              },
              {
                "Timestamp": 1766095200,
                "Value": 20401174
              },
              {
                "Timestamp": 1766095500,
                "Value": 27150906
              },
              {
                "Timestamp": 1766095800,
                "Value": 25641518
              },
              {
                "Timestamp": 1766096100,
                "Value": 27029288
              },
              {
                "Timestamp": 1766096400,
                "Value": 24106663
              },
              {
                "Timestamp": 1766096700,
                "Value": 26810895
              },
              {
                "Timestamp": 1766097000,
                "Value": 24214469
              },
              {
                "Timestamp": 1766097300,
                "Value": 26484597
              },
              {
                "Timestamp": 1766097600,
                "Value": 25029985
              },
              {
                "Timestamp": 1766097900,
                "Value": 29645387
              },
              {
                "Timestamp": 1766098200,
                "Value": 28865107
              },
              {
                "Timestamp": 1766098500,
                "Value": 25492414
              },
              {
                "Timestamp": 1766098800,
                "Value": 25765605
              },
              {
                "Timestamp": 1766099100,
                "Value": 27181414
              },
              {
                "Timestamp": 1766099400,
                "Value": 26533286
              },
              {
                "Timestamp": 1766099700,
                "Value": 30359817
              },
              {
                "Timestamp": 1766100000,
                "Value": 23908438
              },
              {
                "Timestamp": 1766100300,
                "Value": 22682602
              },
              {
                "Timestamp": 1766100600,
                "Value": 20547871
              },
              {
                "Timestamp": 1766100900,
                "Value": 20031206
              },
              {
                "Timestamp": 1766101200,
                "Value": 20260708
              },
              {
                "Timestamp": 1766101500,
                "Value": 25343571
              },
              {
                "Timestamp": 1766101800,
                "Value": 20819424
              },
              {
                "Timestamp": 1766102100,
                "Value": 15982951
              },
              {
                "Timestamp": 1766102400,
                "Value": 16053826
              },
              {
                "Timestamp": 1766102700,
                "Value": 17405970
              },
              {
                "Timestamp": 1766103000,
                "Value": 18760935
              },
              {
                "Timestamp": 1766103300,
                "Value": 15661830
              },
              {
                "Timestamp": 1766103600,
                "Value": 17483123
              },
              {
                "Timestamp": 1766103900,
                "Value": 20826267
              },
              {
                "Timestamp": 1766104200,
                "Value": 22096317
              },
              {
                "Timestamp": 1766104500,
                "Value": 24577063
              },
              {
                "Timestamp": 1766104800,
                "Value": 22460292
              },
              {
                "Timestamp": 1766105100,
                "Value": 22634033
              },
              {
                "Timestamp": 1766105400,
                "Value": 21061142
              },
              {
                "Timestamp": 1766105700,
                "Value": 19542838
              },
              {
                "Timestamp": 1766106000,
                "Value": 20028629
              },
              {
                "Timestamp": 1766106300,
                "Value": 19475514
              },
              {
                "Timestamp": 1766106600,
                "Value": 19044156
              },
              {
                "Timestamp": 1766106900,
                "Value": 20925989
              },
              {
                "Timestamp": 1766107200,
                "Value": 18357917
              },
              {
                "Timestamp": 1766107500,
                "Value": 15293778
              },
              {
                "Timestamp": 1766107800,
                "Value": 17895930
              },
              {
                "Timestamp": 1766108100,
                "Value": 16726012
              },
              {
                "Timestamp": 1766108400,
                "Value": 21790245
              },
              {
                "Timestamp": 1766108700,
                "Value": 23671035
              },
              {
                "Timestamp": 1766109000,
                "Value": 21259311
              },
              {
                "Timestamp": 1766109300,
                "Value": 21284505
              },
              {
                "Timestamp": 1766109600,
                "Value": 21311544
              },
              {
                "Timestamp": 1766109900,
                "Value": 22159692
              },
              {
                "Timestamp": 1766110200,
                "Value": 27565828
              },
              {
                "Timestamp": 1766110500,
                "Value": 26221347
              }
            ],
            "Max": 298793166,
            "MetricName": "l7Flow_bandwidth",
            "Sum": 6893272169
          }
        ]
      }
    ],
    "RequestId": "2af3ca0b-f7a3-42dd-8465-e71e49a77822",
    "TotalCount": 1
  }
}